module_utilities/__init__.py
module_utilities/_doc.py
module_utilities/_typing_compat.py
module_utilities/attributedict.py
module_utilities/cached.py
module_utilities/docfiller.py
module_utilities/docinherit.py
module_utilities/options.py
module_utilities/py.typed
module_utilities/typing.py
module_utilities/vendored/LICENSE.txt
module_utilities/vendored/README.txt
module_utilities/vendored/__init__.py
module_utilities/vendored/docscrape.py
module_utilities-0.10.1.dist-info/METADATA
module_utilities-0.10.1.dist-info/WHEEL
module_utilities-0.10.1.dist-info/licenses/LICENSE
module_utilities-0.10.1.dist-info/RECORD
