Metadata-Version: 2.4
Name: module-utilities
Version: 0.10.1
Summary: Collection of utilities to aid working with python modules.
Project-URL: Documentation, https://pages.nist.gov/module-utilities/
Project-URL: Homepage, https://github.com/usnistgov/module-utilities
Author-email: "William P. Krekelberg" <wpk@nist.gov>
License: NIST-PD
License-File: LICENSE
Keywords: module-utilities
Classifier: Development Status :: 2 - Pre-Alpha
Classifier: Intended Audience :: Science/Research
Classifier: License :: Public Domain
Classifier: Operating System :: OS Independent
Classifier: Programming Language :: Python
Classifier: Programming Language :: Python :: 3 :: Only
Classifier: Programming Language :: Python :: 3.8
Classifier: Programming Language :: Python :: 3.9
Classifier: Programming Language :: Python :: 3.10
Classifier: Programming Language :: Python :: 3.11
Classifier: Programming Language :: Python :: 3.12
Classifier: Programming Language :: Python :: 3.13
Classifier: Topic :: Scientific/Engineering
Requires-Python: <3.14,>=3.8
Requires-Dist: typing-extensions; python_version < '3.11'
Provides-Extra: all
Requires-Dist: docstring-inheritance; extra == 'all'
Provides-Extra: inherit
Requires-Dist: docstring-inheritance; extra == 'inherit'
